riotskillissue/__init__.py
riotskillissue/auth.py
riotskillissue/cli.py
riotskillissue/static.py
riotskillissue/testing.py
riotskillissue/api/__init__.py
riotskillissue/api/client_mixin.py
riotskillissue/api/models.py
riotskillissue/api/endpoints/account.py
riotskillissue/api/endpoints/champion-mastery.py
riotskillissue/api/endpoints/champion.py
riotskillissue/api/endpoints/champion_mastery.py
riotskillissue/api/endpoints/clash.py
riotskillissue/api/endpoints/league-exp.py
riotskillissue/api/endpoints/league.py
riotskillissue/api/endpoints/league_exp.py
riotskillissue/api/endpoints/lol-challenges.py
riotskillissue/api/endpoints/lol-rso-match.py
riotskillissue/api/endpoints/lol-status.py
riotskillissue/api/endpoints/lol_challenges.py
riotskillissue/api/endpoints/lol_rso_match.py
riotskillissue/api/endpoints/lol_status.py
riotskillissue/api/endpoints/lor-deck.py
riotskillissue/api/endpoints/lor-inventory.py
riotskillissue/api/endpoints/lor-match.py
riotskillissue/api/endpoints/lor-ranked.py
riotskillissue/api/endpoints/lor-status.py
riotskillissue/api/endpoints/lor_deck.py
riotskillissue/api/endpoints/lor_inventory.py
riotskillissue/api/endpoints/lor_match.py
riotskillissue/api/endpoints/lor_ranked.py
riotskillissue/api/endpoints/lor_status.py
riotskillissue/api/endpoints/match.py
riotskillissue/api/endpoints/riftbound-content.py
riotskillissue/api/endpoints/riftbound_content.py
riotskillissue/api/endpoints/spectator-tft.py
riotskillissue/api/endpoints/spectator.py
riotskillissue/api/endpoints/spectator_tft.py
riotskillissue/api/endpoints/summoner.py
riotskillissue/api/endpoints/tft-league.py
riotskillissue/api/endpoints/tft-match.py
riotskillissue/api/endpoints/tft-status.py
riotskillissue/api/endpoints/tft-summoner.py
riotskillissue/api/endpoints/tft_league.py
riotskillissue/api/endpoints/tft_match.py
riotskillissue/api/endpoints/tft_status.py
riotskillissue/api/endpoints/tft_summoner.py
riotskillissue/api/endpoints/tournament-stub.py
riotskillissue-0.1.2.dist-info/METADATA
riotskillissue-0.1.2.dist-info/WHEEL
riotskillissue-0.1.2.dist-info/entry_points.txt
riotskillissue-0.1.2.dist-info/licenses/LICENSE
riotskillissue-0.1.2.dist-info/RECORD
