Metadata-Version: 2.4
Name: riotskillissue
Version: 0.1.2
Summary: Production-ready, auto-updating Riot API wrapper.
Author: Demoen
License-File: LICENSE
Classifier: Development Status :: 4 - Beta
Classifier: Intended Audience :: Developers
Classifier: License :: OSI Approved :: GNU General Public License v3 (GPLv3)
Classifier: Programming Language :: Python :: 3.8
Classifier: Programming Language :: Python :: 3.9
Classifier: Programming Language :: Python :: 3.10
Classifier: Programming Language :: Python :: 3.11
Classifier: Programming Language :: Python :: 3.12
Classifier: Programming Language :: Python :: 3.13
Requires-Python: >=3.8
Requires-Dist: frozendict>=2.4.0
Requires-Dist: httpx>=0.27.0
Requires-Dist: jinja2>=3.1.0
Requires-Dist: msgspec>=0.18.0
Requires-Dist: pydantic>=2.7.0
Requires-Dist: redis>=5.0.0
Requires-Dist: tenacity>=8.2.0
Provides-Extra: dev
Requires-Dist: deepdiff>=6.0.0; extra == 'dev'
Requires-Dist: mypy>=1.10.0; extra == 'dev'
Requires-Dist: pytest-asyncio>=0.23.0; extra == 'dev'
Requires-Dist: pytest-cov>=5.0.0; extra == 'dev'
Requires-Dist: pytest>=8.0.0; extra == 'dev'
Requires-Dist: respx>=0.21.0; extra == 'dev'
Requires-Dist: rich>=13.7.0; extra == 'dev'
Requires-Dist: ruff>=0.4.0; extra == 'dev'
Requires-Dist: typer>=0.12.0; extra == 'dev'
Requires-Dist: types-redis; extra == 'dev'
Requires-Dist: types-requests; extra == 'dev'
